llm_workers_console/__init__.py
llm_workers_console/chat.py
llm_workers_console/chat_completer.py
llm_workers_console/console.py
llm_workers_console-1.0.0.dist-info/METADATA
llm_workers_console-1.0.0.dist-info/WHEEL
llm_workers_console-1.0.0.dist-info/RECORD
