Metadata-Version: 2.3
Name: llm-workers-console
Version: 1.0.0
Summary: Console UI components for LLM Workers - interactive chat interface and rich terminal output
Author: Dmitry Mikhaylov
Author-email: mikhailov.dmitry@gmail.com
Requires-Python: >=3.12,<3.15
Classifier: Programming Language :: Python :: 3
Classifier: Programming Language :: Python :: 3.12
Classifier: Programming Language :: Python :: 3.13
Requires-Dist: llm-workers (==1.0.0)
Requires-Dist: prompt-toolkit (==3.0.50)
Requires-Dist: rich (>=14.1.0,<15.0.0)
Project-URL: Homepage, https://mrbagheera.github.io/llm-workers/
Project-URL: Issues, https://github.com/MrBagheera/llm-workers/issues
